[{"n":"권봉석","r":"부회장","d":"사외이사","div":"경영지원","p":0,"w":0,"s":"남"},{"n":"류재철","r":"사장","d":"H&A사업본부장","div":"H&A","p":0,"w":0,"s":"남"},{"n":"박일평","r":"사장","d":"LG사이언스파크 대표","div":"CTO·연구","p":0,"w":0,"s":"남"},{"n":"조주완","r":"사장","d":"사내이사(경영진)","div":"경영지원","p":0,"w":0,"s":"남"},{"n":"김병훈","r":"부사장","d":"CTO","div":"CTO·연구","p":0,"w":0,"s":"남"},{"n":"김영락","r":"부사장","d":"한국영업본부장","div":"한국영업","p":0,"w":0,"s":"남"},{"n":"김창태","r":"부사장","d":"CFO","div":"경영지원","p":0,"w":0,"s":"남"},{"n":"박형세","r":"부사장","d":"HE사업본부장","div":"HE","p":0,"w":0,"s":"남"},{"n":"배두용","r":"부사장","d":"CFO부문 산하","div":"경영지원","p":0,"w":0,"s":"남"},{"n":"백승태","r":"부사장","d":"리빙솔루션사업부장","div":"H&A","p":0,"w":0,"s":"남"},{"n":"오세기","r":"부사장","d":"H&A연구센터장","div":"H&A","p":0,"w":0,"s":"남"},{"n":"유원","r":"부사장","d":"커뮤니케이션센터장","div":"기타","p":0,"w":0,"s":"남"},{"n":"윤태봉","r":"부사장","d":"해외영업본부장","div":"해외·지역","p":0,"w":0,"s":"남"},{"n":"은석현","r":"부사장","d":"VS사업본부장","div":"VS","p":0,"w":0,"s":"남"},{"n":"이삼수","r":"부사장","d":"CSO","div":"경영지원","p":0,"w":0,"s":"남"},{"n":"이재성","r":"부사장","d":"에어솔루션사업부장","div":"H&A","p":0,"w":0,"s":"남"},{"n":"이재웅","r":"부사장","d":"법무그룹장","div":"경영지원","p":0,"w":0,"s":"남"},{"n":"이천국","r":"부사장","d":"유럽지역대표","div":"해외·지역","p":0,"w":0,"s":"남"},{"n":"이철배","r":"부사장","d":"CX센터장","div":"전사센터·생산","p":0,"w":0,"s":"남"},{"n":"장익환","r":"부사장","d":"BS사업본부장","div":"BS","p":0,"w":0,"s":"남"},{"n":"정규황","r":"부사장","d":"북미지역대표","div":"해외·지역","p":0,"w":0,"s":"남"},{"n":"정기현","r":"부사장","d":"플랫폼사업센터장","div":"기타","p":0,"w":0,"s":"남"},{"n":"정대화","r":"부사장","d":"생산기술원장","div":"CTO·연구","p":0,"w":0,"s":"남"},{"n":"정수화","r":"부사장","d":"장비기술센터장","div":"전사센터·생산","p":0,"w":0,"s":"남"},{"n":"정연채","r":"부사장","d":"고객가치혁신부문장","div":"한국영업","p":0,"w":0,"s":"남"},{"n":"곽도영","r":"전무","d":"냉장고사업담당","div":"H&A","p":0,"w":0,"s":"남"},{"n":"김동욱","r":"전무","d":"B2B선행기술센터장","div":"CTO·연구","p":0,"w":0,"s":"남"},{"n":"김병열","r":"전무","d":"생산혁신센터장","div":"전사센터·생산","p":0,"w":0,"s":"남"},{"n":"김상용","r":"전무","d":"미국HA","div":"기타","p":0,"w":0,"s":"남"},{"n":"김양순","r":"전무","d":"부품솔루션사업부장","div":"기타","p":0,"w":0,"s":"남"},{"n":"김원범","r":"전무","d":"CHO","div":"경영지원","p":0,"w":0,"s":"남"},{"n":"김종용","r":"전무","d":"한국B2C그룹장","div":"한국영업","p":0,"w":0,"s":"남"},{"n":"김종필","r":"전무","d":"품질경영센터장","div":"전사센터·생산","p":0,"w":0,"s":"남"},{"n":"김진경","r":"전무","d":"SoC센터장","div":"CTO·연구","p":0,"w":0,"s":"남"},{"n":"박상호","r":"전무","d":"글로벌경영관리그룹장","div":"경영지원","p":0,"w":0,"s":"남"},{"n":"박인성","r":"전무","d":"SW센터장","div":"CTO·연구","p":0,"w":0,"s":"남"},{"n":"박평구","r":"전무","d":"CRO부문 산하","div":"기타","p":0,"w":0,"s":"남"},{"n":"박희욱","r":"전무","d":"H&A상품기획담당","div":"H&A","p":0,"w":0,"s":"남"},{"n":"백기문","r":"전무","d":"ID사업부장","div":"BS","p":0,"w":0,"s":"남"},{"n":"서영재","r":"전무","d":"BS본부 산하","div":"BS","p":0,"w":0,"s":"남"},{"n":"송성원","r":"전무","d":"중남미지역대표","div":"해외·지역","p":0,"w":0,"s":"남"},{"n":"신석홍","r":"전무","d":"독일법인장","div":"해외·지역","p":0,"w":0,"s":"남"},{"n":"안준홍","r":"전무","d":"정도경영센터장","div":"경영지원","p":0,"w":0,"s":"남"},{"n":"오세천","r":"전무","d":"홍보담당","div":"경영지원","p":0,"w":0,"s":"남"},{"n":"왕철민","r":"전무","d":"글로벌오퍼레이션센터장","div":"전사센터·생산","p":0,"w":0,"s":"남"},{"n":"우종진","r":"전무","d":"BS연구소장","div":"BS","p":0,"w":0,"s":"남"},{"n":"유병헌","r":"전무","d":"북미경영관리담당","div":"해외·지역","p":0,"w":0,"s":"남"},{"n":"유성준","r":"전무","d":"노경담당","div":"경영지원","p":0,"w":0,"s":"남"},{"n":"윤대식","r":"전무","d":"대외협력담당","div":"경영지원","p":0,"w":0,"s":"남"},{"n":"이동선","r":"전무","d":"중국법인장","div":"해외·지역","p":0,"w":0,"s":"남"},{"n":"이상용","r":"전무","d":"VS연구소장","div":"VS","p":0,"w":0,"s":"남"},{"n":"이석우","r":"전무","d":"북미이노베이션센터장","div":"해외·지역","p":0,"w":0,"s":"남"},{"n":"이일환","r":"전무","d":"중아지역대표","div":"해외·지역","p":0,"w":0,"s":"남"},{"n":"이재현","r":"전무","d":"H&A오퍼레이션그룹장","div":"H&A","p":0,"w":0,"s":"남"},{"n":"이정석","r":"전무","d":"오디오사업담당","div":"HE","p":0,"w":0,"s":"남"},{"n":"이충환","r":"전무","d":"TV사업운영센터장","div":"HE","p":0,"w":0,"s":"남"},{"n":"이현욱","r":"전무","d":"키친솔루션사업부장","div":"H&A","p":0,"w":0,"s":"남"},{"n":"임병대","r":"전무","d":"미국법인 산하","div":"기타","p":0,"w":0,"s":"남"},{"n":"장진혁","r":"전무","d":"한국온라인그룹장","div":"한국영업","p":0,"w":0,"s":"남"},{"n":"정재철","r":"전무","d":"HE연구소장","div":"HE","p":0,"w":0,"s":"남"},{"n":"정필원","r":"전무","d":"TV해외영업그룹장","div":"HE","p":0,"w":0,"s":"남"},{"n":"조병하","r":"전무","d":"HE플랫폼사업담당","div":"HE","p":0,"w":0,"s":"남"},{"n":"조휘재","r":"전무","d":"IP센터장","div":"CTO·연구","p":0,"w":0,"s":"남"},{"n":"진심원","r":"전무","d":"에어솔루션연구소장","div":"H&A","p":0,"w":0,"s":"남"},{"n":"최성봉","r":"전무","d":"빌트인/쿠킹사업담당","div":"기타","p":0,"w":0,"s":"남"},{"n":"허재철","r":"전무","d":"한국B2B그룹장","div":"한국영업","p":0,"w":0,"s":"남"},{"n":"황성걸","r":"전무","d":"디자인경영센터장","div":"전사센터·생산","p":0,"w":0,"s":"남"},{"n":"황원용","r":"전무","d":"VS오퍼레이션그룹장","div":"VS","p":0,"w":0,"s":"남"},{"n":"강길성","r":"상무","d":"세무담당","div":"경영지원","p":0,"w":0,"s":"남"},{"n":"강석판","r":"상무","d":"HE본부 산하","div":"HE","p":0,"w":0,"s":"남"},{"n":"강성진","r":"상무","d":"사업기획담당","div":"기타","p":0,"w":0,"s":"남"},{"n":"강승원","r":"상무","d":"아시아경영관리담당","div":"해외·지역","p":0,"w":0,"s":"남"},{"n":"강진용","r":"상무","d":"신뢰성/개발품질담당","div":"전사센터·생산","p":0,"w":0,"s":"남"},{"n":"공성배","r":"상무","d":"검사기술담당","div":"전사센터·생산","p":0,"w":0,"s":"남"},{"n":"곽정호","r":"상무","d":"HE서비스플랫폼개발담당","div":"HE","p":0,"w":0,"s":"남"},{"n":"구지영","r":"상무","d":"CX전략담당","div":"전사센터·생산","p":0,"w":0,"s":"여"},{"n":"권순욱","r":"상무","d":"B2B유럽사업담당","div":"한국영업","p":0,"w":0,"s":"남"},{"n":"권순일","r":"상무","d":"안전환경그룹장","div":"전사센터·생산","p":0,"w":0,"s":"남"},{"n":"권혁진","r":"상무","d":"LSR고객연구소장","div":"CTO·연구","p":0,"w":0,"s":"여"},{"n":"김건우","r":"상무","d":"플랫폼사업센터 산하","div":"기타","p":0,"w":0,"s":"남"},{"n":"김건욱","r":"상무","d":"XR사업담당","div":"기타","p":0,"w":0,"s":"남"},{"n":"김경남","r":"상무","d":"몬테레이생산법인장","div":"해외·지역","p":0,"w":0,"s":"남"},{"n":"김경락","r":"상무","d":"VS연구소 산하","div":"VS","p":0,"w":0,"s":"남"},{"n":"김남수","r":"상무","d":"업무혁신담당 산하","div":"기타","p":0,"w":0,"s":"남"},{"n":"김동원","r":"상무","d":"H&A기반기술연구소장","div":"H&A","p":0,"w":0,"s":"남"},{"n":"김동필","r":"상무","d":"BS본부 산하","div":"BS","p":0,"w":0,"s":"남"},{"n":"김명수","r":"상무","d":"H&A본부 산하","div":"H&A","p":0,"w":0,"s":"남"},{"n":"김명욱","r":"상무","d":"IT개발담당 산하","div":"BS","p":0,"w":0,"s":"남"},{"n":"김민수","r":"상무","d":"사이언스파크기술전략담당","div":"CTO·연구","p":0,"w":0,"s":"남"},{"n":"김사녕","r":"상무","d":"걸프법인장","div":"해외·지역","p":0,"w":0,"s":"남"},{"n":"김상렬","r":"상무","d":"생산기술원 산하","div":"CTO·연구","p":0,"w":0,"s":"남"},{"n":"김석규","r":"상무","d":"선행생산기술연구소장","div":"CTO·연구","p":0,"w":0,"s":"남"},{"n":"김선형","r":"상무","d":"한국영업본부 산하","div":"한국영업","p":0,"w":0,"s":"남"},{"n":"김성재","r":"상무","d":"H&A해외영업그룹장","div":"H&A","p":0,"w":0,"s":"남"},{"n":"김성호","r":"상무","d":"BS본부 산하","div":"BS","p":0,"w":0,"s":"남"},{"n":"김승종","r":"상무","d":"VS유럽영업/PM담당","div":"VS","p":0,"w":0,"s":"남"},{"n":"김영수","r":"상무","d":"리빙솔루션연구소장","div":"H&A","p":0,"w":0,"s":"남"},{"n":"김용국","r":"상무","d":"전략법무담당","div":"경영지원","p":0,"w":0,"s":"남"},{"n":"김용석","r":"상무","d":"경영전략담당","div":"경영지원","p":0,"w":0,"s":"남"},{"n":"김용진","r":"상무","d":"전자생산기술담당","div":"전사센터·생산","p":0,"w":0,"s":"남"},{"n":"김우섭","r":"상무","d":"대외협력담당 산하","div":"경영지원","p":0,"w":0,"s":"남"},{"n":"김운태","r":"상무","d":"H&A본부 산하","div":"H&A","p":0,"w":0,"s":"남"},{"n":"김의도","r":"상무","d":"TV유럽/CIS영업담당","div":"HE","p":0,"w":0,"s":"남"},{"n":"김이권","r":"상무","d":"H&A경영관리담당","div":"H&A","p":0,"w":0,"s":"남"},{"n":"김일욱","r":"상무","d":"리빙솔루션제어연구담당","div":"H&A","p":0,"w":0,"s":"남"},{"n":"김재승","r":"상무","d":"아시아지역대표","div":"해외·지역","p":0,"w":0,"s":"남"},{"n":"김재일","r":"상무","d":"푸네생산법인장","div":"해외·지역","p":0,"w":0,"s":"남"},{"n":"김재철","r":"상무","d":"인공지능연구소 산하","div":"CTO·연구","p":0,"w":0,"s":"남"},{"n":"김종호","r":"상무","d":"H&A해외영업그룹 산하","div":"H&A","p":0,"w":0,"s":"남"},{"n":"김주용","r":"상무","d":"VS경영관리담당","div":"VS","p":0,"w":0,"s":"남"},{"n":"김진규","r":"상무","d":"LED사업담당 산하","div":"HE","p":0,"w":0,"s":"남"},{"n":"김찬수","r":"상무","d":"플랫폼개발담당","div":"기타","p":0,"w":0,"s":"남"},{"n":"김창민","r":"상무","d":"H&A품질경영그룹장","div":"H&A","p":0,"w":0,"s":"남"},{"n":"김철","r":"상무","d":"부품솔루션생산담당","div":"전사센터·생산","p":0,"w":0,"s":"남"},{"n":"김철민","r":"상무","d":"오디오사업담당 산하","div":"HE","p":0,"w":0,"s":"남"},{"n":"김태년","r":"상무","d":"HE생산담당","div":"HE","p":0,"w":0,"s":"남"},{"n":"김태완","r":"상무","d":"세탁기사업담당","div":"H&A","p":0,"w":0,"s":"남"},{"n":"김태훈","r":"상무","d":"이집트법인장","div":"해외·지역","p":0,"w":0,"s":"남"},{"n":"김학현","r":"상무","d":"카자흐스탄법인장","div":"해외·지역","p":0,"w":0,"s":"남"},{"n":"김혁기","r":"상무","d":"프랑스법인장","div":"해외·지역","p":0,"w":0,"s":"남"},{"n":"김형수","r":"상무","d":"북미HE","div":"HE","p":0,"w":0,"s":"남"},{"n":"김효은","r":"상무","d":"브랜드매니지먼트담당","div":"기타","p":0,"w":0,"s":"여"},{"n":"남혜성","r":"상무","d":"홈뷰티사업담당","div":"기타","p":0,"w":0,"s":"여"},{"n":"노규찬","r":"상무","d":"BS로봇사업담당","div":"BS","p":0,"w":0,"s":"남"},{"n":"노숙희","r":"상무","d":"베네룩스법인장","div":"해외·지역","p":0,"w":0,"s":"여"},{"n":"노영남","r":"상무","d":"러시아법인장","div":"해외·지역","p":0,"w":0,"s":"남"},{"n":"노영호","r":"상무","d":"H&A본부 산하","div":"H&A","p":0,"w":0,"s":"남"},{"n":"류승호","r":"상무","d":"ID개발담당","div":"BS","p":0,"w":0,"s":"남"},{"n":"류안동","r":"상무","d":"TV중아영업담당","div":"HE","p":0,"w":0,"s":"남"},{"n":"문병헌","r":"상무","d":"VS생산담당","div":"VS","p":0,"w":0,"s":"남"},{"n":"민동선","r":"상무","d":"북미BS영업담당","div":"BS","p":0,"w":0,"s":"남"},{"n":"민홍기","r":"상무","d":"VS경영전략담당","div":"VS","p":0,"w":0,"s":"남"},{"n":"박근직","r":"상무","d":"찌비뚱생산법인장","div":"해외·지역","p":0,"w":0,"s":"남"},{"n":"박동선","r":"상무","d":"SW플랫폼연구소 산하","div":"CTO·연구","p":0,"w":0,"s":"남"},{"n":"박병주","r":"상무","d":"한국영업전략담당","div":"한국영업","p":0,"w":0,"s":"남"},{"n":"박상현","r":"상무","d":"미국서비스법인장","div":"해외·지역","p":0,"w":0,"s":"남"},{"n":"박영은","r":"상무","d":"한국외대","div":"한국영업","p":0,"w":0,"s":"남"},{"n":"박용호","r":"상무","d":"태국생산법인장","div":"해외·지역","p":0,"w":0,"s":"남"},{"n":"박재성","r":"상무","d":"한국시스템수도권담당","div":"한국영업","p":0,"w":0,"s":"남"},{"n":"박정원","r":"상무","d":"키친솔루션사업부 산하","div":"H&A","p":0,"w":0,"s":"남"},{"n":"박종선","r":"상무","d":"VS연구소 산하","div":"VS","p":0,"w":0,"s":"남"},{"n":"박종원","r":"상무","d":"품질경영센터 산하","div":"전사센터·생산","p":0,"w":0,"s":"남"},{"n":"박준성","r":"상무","d":"한국커머셜기업2담당","div":"한국영업","p":0,"w":0,"s":"남"},{"n":"박준은","r":"상무","d":"VS아시아영업/PM담당","div":"VS","p":0,"w":0,"s":"남"},{"n":"박충현","r":"상무","d":"경영관리담당","div":"경영지원","p":0,"w":0,"s":"남"},{"n":"박태인","r":"상무","d":"H&A스마트제어연구소장","div":"H&A","p":0,"w":0,"s":"남"},{"n":"반병선","r":"상무","d":"유럽경영관리담당","div":"해외·지역","p":0,"w":0,"s":"남"},{"n":"배정현","r":"상무","d":"SAC사업담당","div":"기타","p":0,"w":0,"s":"남"},{"n":"백선필","r":"상무","d":"HE상품기획담당","div":"HE","p":0,"w":0,"s":"남"},{"n":"백승민","r":"상무","d":"로봇선행연구소장","div":"BS","p":0,"w":0,"s":"남"},{"n":"백찬","r":"상무","d":"VS베트남생산법인장","div":"VS","p":0,"w":0,"s":"남"},{"n":"백태권","r":"상무","d":"마그렙법인장","div":"해외·지역","p":0,"w":0,"s":"남"},{"n":"변효식","r":"상무","d":"키친솔루션생산담당","div":"H&A","p":0,"w":0,"s":"남"},{"n":"서동명","r":"상무","d":"인도경영관리담당","div":"해외·지역","p":0,"w":0,"s":"남"},{"n":"서영무","r":"상무","d":"마나우스생산법인장","div":"해외·지역","p":0,"w":0,"s":"남"},{"n":"서정원","r":"상무","d":"업무혁신담당","div":"기타","p":0,"w":0,"s":"남"},{"n":"서흥규","r":"상무","d":"EV충전사업담당","div":"기타","p":0,"w":0,"s":"남"},{"n":"손대기","r":"상무","d":"한국혼매유통담당","div":"한국영업","p":0,"w":0,"s":"남"},{"n":"손진석","r":"상무","d":"해외영업경영관리담당","div":"해외·지역","p":0,"w":0,"s":"남"},{"n":"손창우","r":"상무","d":"테네시생산법인장","div":"해외·지역","p":0,"w":0,"s":"남"},{"n":"손태익","r":"상무","d":"어플라이언스중아영업담당","div":"해외·지역","p":0,"w":0,"s":"남"},{"n":"송계영","r":"상무","d":"키친솔루션연구소장","div":"H&A","p":0,"w":0,"s":"남"},{"n":"송시용","r":"상무","d":"Smart Factory사업담당","div":"기타","p":0,"w":0,"s":"남"},{"n":"송영한","r":"상무","d":"IP사업개발담당","div":"기타","p":0,"w":0,"s":"남"},{"n":"송익환","r":"상무","d":"베트남법인장","div":"한국영업","p":0,"w":0,"s":"남"},{"n":"송준명","r":"상무","d":"H&A경영전략담당","div":"H&A","p":0,"w":0,"s":"남"},{"n":"송홍성","r":"상무","d":"LED개발담당","div":"HE","p":0,"w":0,"s":"남"},{"n":"신동훈","r":"상무","d":"한국영업경영관리담당","div":"한국영업","p":0,"w":0,"s":"남"},{"n":"신정은","r":"상무","d":"B2B선행기술센터 산하","div":"CTO·연구","p":0,"w":0,"s":"여"},{"n":"신현재","r":"상무","d":"키친솔루션제어연구담당","div":"H&A","p":0,"w":0,"s":"남"},{"n":"신효식","r":"상무","d":"IT개발담당 산하","div":"BS","p":0,"w":0,"s":"남"},{"n":"심상보","r":"상무","d":"경영개선담당 산하","div":"경영지원","p":0,"w":0,"s":"남"},{"n":"안경모","r":"상무","d":"HE디자인연구소장","div":"HE","p":0,"w":0,"s":"남"},{"n":"안득수","r":"상무","d":"HE본부 산하","div":"HE","p":0,"w":0,"s":"남"},{"n":"안혁성","r":"상무","d":"북미AS","div":"해외·지역","p":0,"w":0,"s":"남"},{"n":"양정휴","r":"상무","d":"SoC기반기술연구소장","div":"CTO·연구","p":0,"w":0,"s":"남"},{"n":"양희구","r":"상무","d":"제조Solution&Platform센터장 서울대(석사)","div":"기타","p":0,"w":0,"s":"남"},{"n":"엄위상","r":"상무","d":"Software공학연구소장","div":"CTO·연구","p":0,"w":0,"s":"남"},{"n":"여인관","r":"상무","d":"CTO부문 산하","div":"CTO·연구","p":0,"w":0,"s":"남"},{"n":"여창욱","r":"상무","d":"칠레법인장","div":"해외·지역","p":0,"w":0,"s":"남"},{"n":"오상훈","r":"상무","d":"H&A SCM담당","div":"H&A","p":0,"w":0,"s":"남"},{"n":"오성훈","r":"상무","d":"H&A제어품질담당","div":"H&A","p":0,"w":0,"s":"남"},{"n":"오승진","r":"상무","d":"한국HE/BS마케팅담당","div":"HE","p":0,"w":0,"s":"남"},{"n":"오재윤","r":"상무","d":"H&A전력전자연구소장","div":"H&A","p":0,"w":0,"s":"남"},{"n":"오해진","r":"상무","d":"VS북미법인장","div":"VS","p":0,"w":0,"s":"남"},{"n":"오혜원","r":"상무","d":"HE브랜드커뮤니케이션담당","div":"HE","p":0,"w":0,"s":"여"},{"n":"우덕구","r":"상무","d":"VS품질경영담당","div":"VS","p":0,"w":0,"s":"남"},{"n":"우람찬","r":"상무","d":"플랫폼사업센터 산하","div":"H&A","p":0,"w":0,"s":"남"},{"n":"원종화","r":"상무","d":"ID해외영업담당","div":"BS","p":0,"w":0,"s":"남"},{"n":"유시목","r":"상무","d":"HE모듈구매담당","div":"HE","p":0,"w":0,"s":"남"},{"n":"유재섭","r":"상무","d":"고객가치혁신부문 산하","div":"전사센터·생산","p":0,"w":0,"s":"남"},{"n":"윤성일","r":"상무","d":"한국키친솔루션마케팅담당","div":"H&A","p":0,"w":0,"s":"남"},{"n":"이강원","r":"상무","d":"webOS SW개발그룹장","div":"HE","p":0,"w":0,"s":"남"},{"n":"이길노","r":"상무","d":"H&A HR담당","div":"H&A","p":0,"w":0,"s":"남"},{"n":"이동언","r":"상무","d":"튀르키예법인장","div":"해외·지역","p":0,"w":0,"s":"남"},{"n":"이민","r":"상무","d":"HE본부 산하","div":"HE","p":0,"w":0,"s":"남"},{"n":"이범섭","r":"상무","d":"법인역량강화담당","div":"기타","p":0,"w":0,"s":"남"},{"n":"이범철","r":"상무","d":"CSO부문 산하","div":"경영지원","p":0,"w":0,"s":"남"},{"n":"이병훈","r":"상무","d":"한국온라인오픈마켓가전담당","div":"H&A","p":0,"w":0,"s":"남"},{"n":"이상봉","r":"상무","d":"한국온라인종합몰담당","div":"한국영업","p":0,"w":0,"s":"남"},{"n":"이석수","r":"상무","d":"iLab장","div":"기타","p":0,"w":0,"s":"남"},{"n":"이석수","r":"상무","d":"SoC센터 산하","div":"CTO·연구","p":0,"w":0,"s":"남"},{"n":"이성진","r":"상무","d":"구독영업담당","div":"기타","p":0,"w":0,"s":"남"},{"n":"이소연","r":"상무","d":"인도네시아개발담당","div":"해외·지역","p":0,"w":0,"s":"여"},{"n":"이승규","r":"상무","d":"광학연구소장","div":"CTO·연구","p":0,"w":0,"s":"남"},{"n":"이승기","r":"상무","d":"전지장비기술센터장","div":"전사센터·생산","p":0,"w":0,"s":"남"},{"n":"이용찬","r":"상무","d":"모듈기술담당","div":"기타","p":0,"w":0,"s":"남"},{"n":"이윤석","r":"상무","d":"IT사업부장","div":"BS","p":0,"w":0,"s":"남"},{"n":"이재승","r":"상무","d":"H&A구매담당","div":"H&A","p":0,"w":0,"s":"남"},{"n":"이재천","r":"상무","d":"VS오퍼레이션그룹 산하","div":"VS","p":0,"w":0,"s":"남"},{"n":"이정두","r":"상무","d":"이태리법인장","div":"해외·지역","p":0,"w":0,"s":"남"},{"n":"이정희","r":"상무","d":"HE경영관리담당","div":"HE","p":0,"w":0,"s":"남"},{"n":"이종호","r":"상무","d":"사우디생산법인장","div":"해외·지역","p":0,"w":0,"s":"남"},{"n":"이준성","r":"상무","d":"C&M표준연구소 산하","div":"CTO·연구","p":0,"w":0,"s":"남"},{"n":"이준행","r":"상무","d":"ID CX담당","div":"BS","p":0,"w":0,"s":"남"},{"n":"이춘택","r":"상무","d":"에어솔루션생산담당","div":"H&A","p":0,"w":0,"s":"남"},{"n":"이충섭","r":"상무","d":"미래투자담당","div":"기타","p":0,"w":0,"s":"남"},{"n":"이태진","r":"상무","d":"인도네시아법인장","div":"해외·지역","p":0,"w":0,"s":"남"},{"n":"이한욱","r":"상무","d":"VS SW개발담당","div":"VS","p":0,"w":0,"s":"남"},{"n":"이향은","r":"상무","d":"H&A CX담당","div":"H&A","p":0,"w":0,"s":"여"},{"n":"이현진","r":"상무","d":"생산기획담당","div":"전사센터·생산","p":0,"w":0,"s":"남"},{"n":"이형일","r":"상무","d":"TV제품개발담당","div":"HE","p":0,"w":0,"s":"남"},{"n":"임광훈","r":"상무","d":"HE경영전략담당","div":"HE","p":0,"w":0,"s":"남"},{"n":"임기용","r":"상무","d":"캐나다법인장","div":"해외·지역","p":0,"w":0,"s":"남"},{"n":"임대진","r":"상무","d":"BS연구소 산하","div":"BS","p":0,"w":0,"s":"남"},{"n":"임병록","r":"상무","d":"사업법무담당","div":"경영지원","p":0,"w":0,"s":"남"},{"n":"임상무","r":"상무","d":"호주법인장","div":"해외·지역","p":0,"w":0,"s":"남"},{"n":"임정수","r":"상무","d":"구독사업담당","div":"기타","p":0,"w":0,"s":"남"},{"n":"장보영","r":"상무","d":"H&A기술전략담당","div":"H&A","p":0,"w":0,"s":"남"},{"n":"장석진","r":"상무","d":"스마트모빌리티연구소장","div":"CTO·연구","p":0,"w":0,"s":"남"},{"n":"장석호","r":"상무","d":"IT개발담당","div":"BS","p":0,"w":0,"s":"남"},{"n":"장정훈","r":"상무","d":"홍보담당 산하","div":"경영지원","p":0,"w":0,"s":"남"},{"n":"장진호","r":"상무","d":"IP경영담당","div":"경영지원","p":0,"w":0,"s":"남"},{"n":"장차규","r":"상무","d":"H&A본부 산하","div":"H&A","p":0,"w":0,"s":"남"},{"n":"장태진","r":"상무","d":"고객가치혁신CS전략담당","div":"전사센터·생산","p":0,"w":0,"s":"남"},{"n":"전홍걸","r":"상무","d":"VS연구소 산하","div":"VS","p":0,"w":0,"s":"남"},{"n":"전홍주","r":"상무","d":"인도법인장","div":"해외·지역","p":0,"w":0,"s":"남"},{"n":"정대희","r":"상무","d":"Dishwasher사업담당","div":"기타","p":0,"w":0,"s":"남"},{"n":"정상호","r":"상무","d":"냉장고사업담당 산하","div":"H&A","p":0,"w":0,"s":"남"},{"n":"정성한","r":"상무","d":"태국법인장","div":"한국영업","p":0,"w":0,"s":"남"},{"n":"정수진","r":"상무","d":"한국브랜드커뮤니케이션담당","div":"한국영업","p":0,"w":0,"s":"여"},{"n":"정순호","r":"상무","d":"D2C사업그룹장","div":"기타","p":0,"w":0,"s":"남"},{"n":"정연욱","r":"상무","d":"Thunderbird대(석사)","div":"기타","p":0,"w":0,"s":"남"},{"n":"정영학","r":"상무","d":"레반트법인장","div":"해외·지역","p":0,"w":0,"s":"남"},{"n":"정욱준","r":"상무","d":"H&A디자인연구소장","div":"H&A","p":0,"w":0,"s":"남"},{"n":"정원진","r":"상무","d":"BS경영전략담당","div":"BS","p":0,"w":0,"s":"남"},{"n":"정인식","r":"상무","d":"마곡/인천안전환경/지원담당","div":"전사센터·생산","p":0,"w":0,"s":"남"},{"n":"정재웅","r":"상무","d":"고객가치혁신한국서비스담당","div":"한국영업","p":0,"w":0,"s":"남"},{"n":"정재훈","r":"상무","d":"땅그랑생산법인장","div":"해외·지역","p":0,"w":0,"s":"남"},{"n":"정진우","r":"상무","d":"H&A본부 산하","div":"H&A","p":0,"w":0,"s":"남"},{"n":"정호중","r":"상무","d":"CTO부문 산하","div":"CTO·연구","p":0,"w":0,"s":"남"},{"n":"제영호","r":"상무","d":"C&M표준연구소장","div":"CTO·연구","p":0,"w":0,"s":"남"},{"n":"조봉수","r":"상무","d":"AI빅데이터담당","div":"기타","p":0,"w":0,"s":"남"},{"n":"조서린","r":"상무","d":"VS HR담당","div":"VS","p":0,"w":0,"s":"남"},{"n":"조성구","r":"상무","d":"디자인경영센터 산하","div":"전사센터·생산","p":0,"w":0,"s":"남"},{"n":"조성태","r":"상무","d":"VS한국영업/PM담당","div":"VS","p":0,"w":0,"s":"남"},{"n":"조정범","r":"상무","d":"DX전략담당","div":"전사센터·생산","p":0,"w":0,"s":"남"},{"n":"조청대","r":"상무","d":"한국시스템지역담당","div":"한국영업","p":0,"w":0,"s":"남"},{"n":"조협","r":"상무","d":"한국커머셜지역담당","div":"한국영업","p":0,"w":0,"s":"남"},{"n":"지형섭","r":"상무","d":"나이지리아법인장","div":"해외·지역","p":0,"w":0,"s":"남"},{"n":"차현승","r":"상무","d":"오디오사업담당 산하","div":"HE","p":0,"w":0,"s":"남"},{"n":"최규남","r":"상무","d":"BS육성버티컬영업담당","div":"BS","p":0,"w":0,"s":"남"},{"n":"최봉현","r":"상무","d":"HE품질경영담당","div":"HE","p":0,"w":0,"s":"남"},{"n":"최승윤","r":"상무","d":"HE구매담당","div":"HE","p":0,"w":0,"s":"남"},{"n":"최윤호","r":"상무","d":"소자재료연구소장","div":"CTO·연구","p":0,"w":0,"s":"남"},{"n":"최진학","r":"상무","d":"H&A아웃소싱사업담당","div":"H&A","p":0,"w":0,"s":"남"},{"n":"최활수","r":"상무","d":"영국법인장","div":"해외·지역","p":0,"w":0,"s":"남"},{"n":"하건호","r":"상무","d":"리빙솔루션생산담당","div":"H&A","p":0,"w":0,"s":"남"},{"n":"한은정","r":"상무","d":"인공지능연구소 산하","div":"CTO·연구","p":0,"w":0,"s":"여"},{"n":"한창희","r":"상무","d":"BS HR담당","div":"BS","p":0,"w":0,"s":"남"},{"n":"허순재","r":"상무","d":"멕시코법인장","div":"해외·지역","p":0,"w":0,"s":"남"},{"n":"허정찬","r":"상무","d":"글로벌물류담당","div":"기타","p":0,"w":0,"s":"남"},{"n":"허정호","r":"상무","d":"Aalto대(舊Helsinki경제대)(석사)","div":"기타","p":0,"w":0,"s":"남"},{"n":"홍성표","r":"상무","d":"SW플랫폼연구소장","div":"CTO·연구","p":0,"w":0,"s":"남"},{"n":"홍성혁","r":"상무","d":"레이노사생산법인장","div":"해외·지역","p":0,"w":0,"s":"남"},{"n":"홍순열","r":"상무","d":"에어케어사업담당","div":"기타","p":0,"w":0,"s":"남"},{"n":"홍지삼","r":"상무","d":"한국영업본부 산하","div":"한국영업","p":0,"w":0,"s":"남"},{"n":"홍진기","r":"상무","d":"SCM담당","div":"전사센터·생산","p":0,"w":0,"s":"남"},{"n":"황금식","r":"상무","d":"B2B아시아사업담당","div":"해외·지역","p":0,"w":0,"s":"남"},{"n":"황상문","r":"상무","d":"TV기구/LCM개발담당","div":"HE","p":0,"w":0,"s":"남"},{"n":"황용순","r":"상무","d":"어플라이언스아시아영업담당","div":"해외·지역","p":0,"w":0,"s":"남"},{"n":"황원재","r":"상무","d":"제조DX솔루션담당","div":"전사센터·생산","p":0,"w":0,"s":"남"},{"n":"황재우","r":"상무","d":"CFO부문 산하","div":"경영지원","p":0,"w":0,"s":"남"},{"n":"황종하","r":"상무","d":"경영전략담당 산하","div":"경영지원","p":0,"w":0,"s":"남"},{"n":"강수진","r":"사외이사","d":"사외이사","div":"경영지원","p":0,"w":0,"s":"여"},{"n":"강용석","r":"기타","d":"SoC센터 산하","div":"CTO·연구","p":0,"w":0,"s":"남"},{"n":"김수연","r":"기타","d":"H&A디자인연구소 산하","div":"H&A","p":0,"w":0,"s":"여"},{"n":"김영재","r":"기타","d":"로봇선행연구소 산하","div":"BS","p":0,"w":0,"s":"남"},{"n":"김용태","r":"기타","d":"플랫폼사업센터 산하","div":"기타","p":0,"w":0,"s":"남"},{"n":"류충렬","r":"사외이사","d":"사외이사","div":"경영지원","p":0,"w":0,"s":"남"},{"n":"서승우","r":"사외이사","d":"사외이사","div":"경영지원","p":0,"w":0,"s":"남"},{"n":"서한별","r":"기타","d":"C&M표준연구소 산하","div":"CTO·연구","p":0,"w":0,"s":"남"},{"n":"우정훈","r":"기타","d":"H&A본부 산하","div":"H&A","p":0,"w":0,"s":"남"},{"n":"윤영우","r":"기타","d":"C&M표준연구소 산하","div":"CTO·연구","p":0,"w":0,"s":"남"},{"n":"이상구","r":"사외이사","d":"사외이사","div":"경영지원","p":0,"w":0,"s":"남"},{"n":"임효준","r":"기타","d":"SW플랫폼연구소 산하","div":"CTO·연구","p":0,"w":0,"s":"남"}]